curp/main.py
consulta_gob-1.0.0.dist-info/LICENSE
consulta_gob-1.0.0.dist-info/METADATA
consulta_gob-1.0.0.dist-info/WHEEL
consulta_gob-1.0.0.dist-info/top_level.txt
consulta_gob-1.0.0.dist-info/RECORD
