Metadata-Version: 2.1
Name: consulta-gob
Version: 1.0.0
Summary: Packete para conultar info relacionada con CURP
Home-page: UNKNOWN
Author: Partum
Author-email: partum.sts@gmail.com
License: MIT
Platform: UNKNOWN
Classifier: Programming Language :: Python :: 3
Classifier: Programming Language :: Python :: 3.7
Classifier: License :: OSI Approved :: MIT License
Classifier: Operating System :: OS Independent
Requires-Dist: requests
